X5FenzhongShangxueyuanJingxiBiji000185/README.md
X5FenzhongShangxueyuanJingxiBiji000185/__init__.py
X5FenzhongShangxueyuanJingxiBiji000185/__main__.py
X5FenzhongShangxueyuanJingxiBiji000185/file.epub
X5FenzhongShangxueyuanJingxiBiji000185/index.html
X5FenzhongShangxueyuanJingxiBiji000185/css/__init__.py
X5FenzhongShangxueyuanJingxiBiji000185/css/annotations.css
X5FenzhongShangxueyuanJingxiBiji000185/css/main.css
X5FenzhongShangxueyuanJingxiBiji000185/css/normalize.css
X5FenzhongShangxueyuanJingxiBiji000185/css/popup.css
X5FenzhongShangxueyuanJingxiBiji000185/font/__init__.py
X5FenzhongShangxueyuanJingxiBiji000185/font/fontello.eot
X5FenzhongShangxueyuanJingxiBiji000185/font/fontello.svg
X5FenzhongShangxueyuanJingxiBiji000185/font/fontello.ttf
X5FenzhongShangxueyuanJingxiBiji000185/font/fontello.woff
X5FenzhongShangxueyuanJingxiBiji000185/img/__init__.py
X5FenzhongShangxueyuanJingxiBiji000185/img/annotator-glyph-sprite.png
X5FenzhongShangxueyuanJingxiBiji000185/img/annotator-icon-sprite.png
X5FenzhongShangxueyuanJingxiBiji000185/img/apple-touch-icon.png
X5FenzhongShangxueyuanJingxiBiji000185/img/cancelfullscreen.png
X5FenzhongShangxueyuanJingxiBiji000185/img/close.png
X5FenzhongShangxueyuanJingxiBiji000185/img/fullscreen.png
X5FenzhongShangxueyuanJingxiBiji000185/img/loader.gif
X5FenzhongShangxueyuanJingxiBiji000185/img/menu-icon.png
X5FenzhongShangxueyuanJingxiBiji000185/img/save.png
X5FenzhongShangxueyuanJingxiBiji000185/img/saved.png
X5FenzhongShangxueyuanJingxiBiji000185/img/settings-s.png
X5FenzhongShangxueyuanJingxiBiji000185/img/settings.png
X5FenzhongShangxueyuanJingxiBiji000185/img/star.png
X5FenzhongShangxueyuanJingxiBiji000185/js/__init__.py
X5FenzhongShangxueyuanJingxiBiji000185/js/epub.js
X5FenzhongShangxueyuanJingxiBiji000185/js/epub.min.js
X5FenzhongShangxueyuanJingxiBiji000185/js/epub.min.map
X5FenzhongShangxueyuanJingxiBiji000185/js/hooks.min.js
X5FenzhongShangxueyuanJingxiBiji000185/js/hooks.min.map
x5_fenzhong_shangxueyuan_jingxi_biji_000_185-2024.3.5.0.dist-info/METADATA
x5_fenzhong_shangxueyuan_jingxi_biji_000_185-2024.3.5.0.dist-info/WHEEL
x5_fenzhong_shangxueyuan_jingxi_biji_000_185-2024.3.5.0.dist-info/entry_points.txt
x5_fenzhong_shangxueyuan_jingxi_biji_000_185-2024.3.5.0.dist-info/top_level.txt
x5_fenzhong_shangxueyuan_jingxi_biji_000_185-2024.3.5.0.dist-info/RECORD
